breezy/plugins/loggerhead/__init__.py
loggerhead/__init__.py
loggerhead/changecache.py
loggerhead/config.py
loggerhead/daemon.py
loggerhead/highlight.py
loggerhead/history.py
loggerhead/load_test.py
loggerhead/lsprof.py
loggerhead/main.py
loggerhead/search.py
loggerhead/templatefunctions.py
loggerhead/util.py
loggerhead/wholehistory.py
loggerhead/zptsupport.py
loggerhead/apps/__init__.py
loggerhead/apps/branch.py
loggerhead/apps/error.py
loggerhead/apps/http_head.py
loggerhead/apps/transport.py
loggerhead/controllers/__init__.py
loggerhead/controllers/annotate_ui.py
loggerhead/controllers/atom_ui.py
loggerhead/controllers/changelog_ui.py
loggerhead/controllers/diff_ui.py
loggerhead/controllers/directory_ui.py
loggerhead/controllers/download_ui.py
loggerhead/controllers/error_ui.py
loggerhead/controllers/filediff_ui.py
loggerhead/controllers/inventory_ui.py
loggerhead/controllers/revision_ui.py
loggerhead/controllers/revlog_ui.py
loggerhead/controllers/search_ui.py
loggerhead/controllers/view_ui.py
loggerhead/middleware/__init__.py
loggerhead/middleware/profile.py
loggerhead/static/css/diff.css
loggerhead/static/css/files.css
loggerhead/static/css/global.css
loggerhead/static/css/highlight.css
loggerhead/static/css/view.css
loggerhead/static/images/bg_Tabs.gif
loggerhead/static/images/bg_infobox.gif
loggerhead/static/images/bg_menuTabs.gif
loggerhead/static/images/bg_search_input.gif
loggerhead/static/images/bg_submenuTabs.gif
loggerhead/static/images/deleteCode.gif
loggerhead/static/images/favicon.ico
loggerhead/static/images/favicon.png
loggerhead/static/images/ico_branch.gif
loggerhead/static/images/ico_bug.png
loggerhead/static/images/ico_committer.gif
loggerhead/static/images/ico_description.gif
loggerhead/static/images/ico_diff.gif
loggerhead/static/images/ico_file.gif
loggerhead/static/images/ico_file_download.gif
loggerhead/static/images/ico_file_flecha.gif
loggerhead/static/images/ico_file_modify.gif
loggerhead/static/images/ico_folder.gif
loggerhead-2.0.1.dist-info/COPYING.txt
loggerhead-2.0.1.dist-info/METADATA
loggerhead-2.0.1.dist-info/WHEEL
loggerhead-2.0.1.dist-info/top_level.txt
loggerhead-2.0.1.dist-info/RECORD
