Metadata-Version: 2.1
Name: loggerhead
Version: 2.0.1
Summary: Loggerhead is a web viewer for projects in bazaar
Maintainer: Michael Hudson
Maintainer-email: michael.hudson@canonical.com
License: GNU GPL v2 or later
License-File: COPYING.txt
Requires-Dist: Chameleon
Requires-Dist: Paste (>=1.6)
Requires-Dist: bleach
Requires-Dist: breezy (>=3.1)
Requires-Dist: packaging
Requires-Dist: importlib-metadata ; python_version < "3.8"
Provides-Extra: flup
Requires-Dist: flup ; extra == 'flup'
Provides-Extra: proxied
Requires-Dist: PasteDeploy (>=1.3) ; extra == 'proxied'
